Workbook

Sheet 1-ЙЎРИҚНОМА
A1: ЭМЖИЕМ — AI АГЕНТЛАР ТРЕКЕРИ · 25.08.2026 · Эгаси учун
A3: БУ ФАЙЛ НИМА? | B3: Қурилиши керак бўлган AI агентларнинг рўйхати ва уларнинг ҳолатини кузатиш жадвали. Ҳар ҳафта якшанба куни очиб, «Ҳолат» устунини янгилаб борилади.
A5: ВАРАҚЛАР | B5: 2-АГЕНТЛАР — асосий рўйхат (21 агент). Шу ерда ишлайсиз.
B6: 3-ХИСОБ — пул ва вақт ҳисоби. Сариқ катакчаларни ўзгартирсангиз ҳамма рақам қайта ҳисобланади.
B7: 4-БЮДЖЕТ — ойлик ва йиллик харажат, 3 та вариант.
B8: 5-РЕЖА — 90 кунлик босқичма-босқич режа.
B9: 6-КЕРАКСИЗ — қурмаслик керак бўлган агентлар ва сабаби. Пулни тежайдиган варақ.
B10: 7-ДАШБОРД — умумий манзара: нечта агент ишлаяпти, нечтаси турибди.
A12: ҚАЙСИ КАТАКНИ ТЎЛДИРАМАН? | B12: САРИҚ фонли катаклар — сиз тўлдирасиз. ОҚ фонли катаклар — формула, тегманг, ўзи ҳисоблайди.
A14: ШОШИЛИНЧЛИК ҚАНДАЙ ҲИСОБЛАНАДИ? | B14: Балл = Пул таъсири (1–10) × Эҳтимол (0.1–1.0) × Тўсиқ коэффициенти (1–3)
B15: Пул таъсири — бу агент компанияга қанча пул олиб келади ёки тежайди (10 = энг кўп).
B16: Эҳтимол — бу агент ҳақиқатан ишлаб кетиш эҳтимоли (1.0 = аниқ ишлайди).
B17: Тўсиқ коэффициенти — бу агент бошқа ишларни очиб берадими? 3 = усиз бошқаси ҳаракатланмайди.
B18: ≥18 = КРИТИК · ≥12 = ШОШИЛИНЧ · ≥4.8 = ОДДИЙ · <4.8 = КЕРАКСИЗ
A20: ОЛТИН ҚОИДА | B20: Бир вақтда фақат 2 та агент қурилади. Учинчиси биттаси ТЎЛИҚ ишлаб кетмагунча бошланмайди.
B21: Сабаб: аудит кўрсатди — 11 та бошланган лойиҳадан фақат 2 таси тугалланган.
A23: ҲАР АГЕНТ УЧУН ТЕКШИРУВ | B23: И = (Агент тўғри бажарган иш сони) ÷ (Жами уриниш сони). И ≥ 0.80 бўлса — ишлаяпти, кейингисига ўтинг.
B24: И < 0.50 бўлса — ТЎХТАНГ. Муаммо технологияда эмас, жараёнда ёки интизомда.

Sheet 2-АГЕНТЛАР
A1: AI АГЕНТЛАР РЎЙХАТИ — 21 та · Сариқ катакларни сиз тўлдирасиз
A2: № | B2: Код | C2: АГЕНТ НОМИ | D2: Блок | E2: НИМА ҚИЛАДИ | F2: НИМА УЧУН КЕРАК (аудит далили) | G2: Платформа | H2: Масъул | I2: ҲОЛАТ | J2: Пул таъсири 1–10 | K2: Эҳтимол 0.1–1 | L2: Тўсиқ коэф. 1–3 | M2: БАЛЛ | N2: ШОШИЛИНЧЛИК | O2: Қуриш вақти, соат | P2: Ойлик вақт тежови, соат | Q2: Йиллик фойда МАКС, $ | R2: Йиллик фойда РЕАЛ, $ | S2: Ойлик харажат, $ | T2: Йиллик харажат, $ | U2: ROI (фақат API), % | V2: Бошланиш | W2: Тугаш
A3: 1 | B3: H0 | C3: AI УЛОВЧИ (МАРКАЗИЙ ҲУБ) | D3: 0. ИНФРАТУЗИЛМА | E3: Барча агентларнинг «электр тармоғи». Telegram, WhatsApp, Instagram, Outlook, Excel, SAP B1 (фақат ўқиш) ва Claude/ChatGPT'ни битта жойда улайди. Ҳар агент шу ҳубнинг ичида битта «занжир» бўлиб яшайди. | F3: Ҳозир ҳар маълумот алоҳида жойда: дафтарча, Telegram, SAP, 1C, Didox. Улар ўзаро гаплашмайди. Ҳуб бўлмаса ҳар агентни нолдан қуриш керак. | G3: n8n (ўз серверда) + Claude API | H3: Абдулбосит (IT) | I3: ЯРАТИЛМАГАН | J3: 9 | K3: 0.9 | L3: 3 | M3: =J3*K3*L3 -> 24.3 | N3: =IF(M3>=18,"КРИТИК",IF(M3>=12,"ШОШИЛИНЧ",IF(M3>=4.8,"ОДДИЙ","КЕРАКСИЗ"))) -> КРИТИК | O3: 16 | P3: 0 | Q3: 0 | R3: =Q3*'3-ХИСОБ'!$B$9 -> 0 | S3: 10 | T3: =S3*12 -> 120 | U3: =IF(T3=0,0,(R3-T3)/T3) -> -1
A4: 2 | B4: A1 | C4: КУНДАЛИК ҲИСОБОТ ЙИҒУВЧИ | D4: A. НАЗОРАТ | E4: Ҳар куни 17:30 да ҳар бир ходимга Telegram орқали ўзи савол беради, жавобни ажратиб жадвалга ёзади, 18:30 да Эгасига битта умумий хулоса юборади. Жавоб бермаганларни рўйхатга олади. | F4: Аудит: ёзма ҳисоботлар бор, лекин фақат Эгаси эслатганда келади. 22 ходимдан фақат 3–4 таси ўзи ишлайди. | G4: n8n + Telegram + Excel/SharePoint + Claude | H4: Муҳаммад | I4: ЯРАТИЛМАГАН | J4: 7 | K4: 0.9 | L4: 3 | M4: =J4*K4*L4 -> 18.9 | N4: =IF(M4>=18,"КРИТИК",IF(M4>=12,"ШОШИЛИНЧ",IF(M4>=4.8,"ОДДИЙ","КЕРАКСИЗ"))) -> КРИТИК | O4: 6 | P4: 22 | Q4: 3000 | R4: =Q4*'3-ХИСОБ'!$B$9 -> 1500 | S4: 8 | T4: =S4*12 -> 96 | U4: =IF(T4=0,0,(R4-T4)/T4) -> 14.625
A5: 3 | B5: A2 | C5: 5 РАҚАМ ДАШБОРДИ | D5: A. НАЗОРАТ | E5: Ҳар куни эрталаб 5 та рақамни битта экранда кўрсатади: касса, кечаги сотув, захира қиймати, мижоз қарзи, бугунги тўловлар. Рақам чегарадан чиқса — дарҳол огоҳлантиради. | F5: Аудит: SAP B1 дан бирорта ҳисобот олинмайди. Эгаси P&L ўқимайди, фақат банк қолдиғига қарайди. Феврал ва март зарар бўлгани ой тугагандан кейин билинди. | G5: n8n + SAP B1 (ўқиш) + Excel + Power BI ёки Telegram | H5: Зайнаб + Абдулбосит | I5: ЯРАТИЛМАГАН | J5: 8 | K5: 0.8 | L5: 3 | M5: =J5*K5*L5 -> 19.2 | N5: =IF(M5>=18,"КРИТИК",IF(M5>=12,"ШОШИЛИНЧ",IF(M5>=4.8,"ОДДИЙ","КЕРАКСИЗ"))) -> КРИТИК | O5: 10 | P5: 12 | Q5: 6000 | R5: =Q5*'3-ХИСОБ'!$B$9 -> 3000 | S5: 10 | T5: =S5*12 -> 120 | U5: =IF(T5=0,0,(R5-T5)/T5) -> 24
A6: 4 | B6: A3 | C6: ТОПШИРИҚ КУЗАТУВЧИ (ТУРТКИ АГЕНТИ) | D6: A. НАЗОРАТ | E6: Йиғилишда ёки чатда берилган ҳар топшириқни ушлаб қолади, муддат қўяди, муддат яқинлашганда эслатади, ўтиб кетса Эгасига хабар беради. Эгаси ҳеч кимни қўлда эслатмайди. | F6: Аудит: 11 та бошланган лойиҳадан 2 таси тугалланган, 6 таси тўхтаган. Ходимлар эслатилмаса ишламайди. | G6: n8n + Telegram + Microsoft Planner/To Do | H6: Муҳаммад | I6: ЯРАТИЛМАГАН | J6: 7 | K6: 0.9 | L6: 3 | M6: =J6*K6*L6 -> 18.9 | N6: =IF(M6>=18,"КРИТИК",IF(M6>=12,"ШОШИЛИНЧ",IF(M6>=4.8,"ОДДИЙ","КЕРАКСИЗ"))) -> КРИТИК | O6: 8 | P6: 20 | Q6: 4000 | R6: =Q6*'3-ХИСОБ'!$B$9 -> 2000 | S6: 6 | T6: =S6*12 -> 72 | U6: =IF(T6=0,0,(R6-T6)/T6) -> 26.777778
A7: 5 | B7: A4 | C7: ДАВОМАТ АГЕНТИ (КИРИШ–ЧИҚИШ) | D7: A. НАЗОРАТ | E7: Ходим ишга келганда ва кетганда Telegram'га белги қўяди (ёки Verifix маълумотини олади), кечикишни санайди, ҳафталик жадвал беради. | F7: Аудит: 3–5 ходим эртага кетса компания ҳеч нарса йўқотмайди — лекин ким қанча ишлаётгани ўлчанмайди. | G7: n8n + Verifix + Telegram | H7: Нодира (HR) | I7: ЯРАТИЛМАГАН | J7: 3 | K7: 0.8 | L7: 2 | M7: =J7*K7*L7 -> 4.8 | N7: =IF(M7>=18,"КРИТИК",IF(M7>=12,"ШОШИЛИНЧ",IF(M7>=4.8,"ОДДИЙ","КЕРАКСИЗ"))) -> ОДДИЙ | O7: 5 | P7: 6 | Q7: 1500 | R7: =Q7*'3-ХИСОБ'!$B$9 -> 750 | S7: 3 | T7: =S7*12 -> 36 | U7: =IF(T7=0,0,(R7-T7)/T7) -> 19.833333
A8: 6 | B8: B1 | C8: ТЎЛОВ ДАРВОЗАСИ | D8: Б. МОЛИЯ | E8: Барча тўлов сўровлари фақат битта Telegram шаклидан ўтади. Агент суммани текширади, лимитдан кам бўлса автоматик рухсат беради, кўп бўлса Эгасига «Ҳа/Йўқ» тугмаси билан юборади. Ҳар тўлов ёзиб борилади. | F8: Аудит: тўлов сўровлари бўлим бошлиқлари, бухгалтерия ва Эгасидан аралаш келади — ягона канал йўқ. Лимит бор, лекин ёзилмаган. | G8: n8n + Telegram + Excel | H8: Улуғбек + Зайнаб | I8: ЯРАТИЛМАГАН | J8: 8 | K8: 0.85 | L8: 3 | M8: =J8*K8*L8 -> 20.4 | N8: =IF(M8>=18,"КРИТИК",IF(M8>=12,"ШОШИЛИНЧ",IF(M8>=4.8,"ОДДИЙ","КЕРАКСИЗ"))) -> КРИТИК | O8: 8 | P8: 10 | Q8: 5000 | R8: =Q8*'3-ХИСОБ'!$B$9 -> 2500 | S8: 5 | T8: =S8*12 -> 60 | U8: =IF(T8=0,0,(R8-T8)/T8) -> 40.666667
A9: 7 | B9: B2 | C9: 30-КУНЛИК ПУЛ КАЛЕНДАРИ | D9: Б. МОЛИЯ | E9: Келгуси 30 кунда қайси кун қанча пул кириши ва чиқиши кутилаётганини кўрсатади. Пул етмайдиган кунни олдиндан қизил қилиб белгилайди. | F9: Аудит: 30 кунлик пул режаси умуман йўқ — тўловлар талаб келганда қилинади. Пул айланиши 145 кун. | G9: n8n + Excel + SAP B1 | H9: Зайнаб | I9: ЯРАТИЛМАГАН | J9: 7 | K9: 0.9 | L9: 3 | M9: =J9*K9*L9 -> 18.9 | N9: =IF(M9>=18,"КРИТИК",IF(M9>=12,"ШОШИЛИНЧ",IF(M9>=4.8,"ОДДИЙ","КЕРАКСИЗ"))) -> КРИТИК | O9: 10 | P9: 8 | Q9: 4000 | R9: =Q9*'3-ХИСОБ'!$B$9 -> 2000 | S9: 6 | T9: =S9*12 -> 72 | U9: =IF(T9=0,0,(R9-T9)/T9) -> 26.777778
A10: 8 | B10: B3 | C10: СОЛИШТИРУВ АГЕНТИ (БАНК ↔ SAP ↔ 1C ↔ Didox) | D10: Б. МОЛИЯ | E10: Ҳар куни тўрт манбадаги рақамни солиштиради ва фарқ чиққан ҳар қаторни рўйхат қилиб беради. Одам фақат фарқни кўради, ҳаммасини эмас. | F10: Аудит: банк ↔ SAP ↔ 1C рақамларини ҳеч ким солиштирмайди. Эгаси айтган 200 млн сўмлик ой бюджети ҳақиқий $32K харажатнинг ярми — яъни харажатнинг ярми кўринмаган. | G10: n8n + SAP B1 + 1C + Didox + Excel | H10: Зайнаб | I10: ЯРАТИЛМАГАН | J10: 8 | K10: 0.8 | L10: 3 | M10: =J10*K10*L10 -> 19.2 | N10: =IF(M10>=18,"КРИТИК",IF(M10>=12,"ШОШИЛИНЧ",IF(M10>=4.8,"ОДДИЙ","КЕРАКСИЗ"))) -> КРИТИК | O10: 14 | P10: 16 | Q10: 8000 | R10: =Q10*'3-ХИСОБ'!$B$9 -> 4000 | S10: 12 | T10: =S10*12 -> 144 | U10: =IF(T10=0,0,(R10-T10)/T10) -> 26.777778
A11: 9 | B11: B4 | C11: ХАТОЛИК ВА ЕТИШМАЁТГАН МАЪЛУМОТ ДЕТЕКТОРИ | D11: Б. МОЛИЯ | E11: Ҳар файл ва базани текширади: таннархи йўқ товар, икки омборда турган бир код, ёпилган лойиҳада қолган мол, санаси йўқ қатор, нархи нолга тенг сатр. Топганини рўйхат қилиб масъулга юборади. | F11: Ўлчанган далил: омбор файлида 182 та код икки омборда — $156,381; ёпилган SPOTX омборларида $99,935 мол; 4 та кимё позициясида таннарх йўқ; 5 позиция 485 кундан бери «кўчада» омборида. | G11: n8n + Claude + Excel + SAP B1 | H11: Отабек + Абдулбосит | I11: ЯРАТИЛМАГАН | J11: 9 | K11: 0.7 | L11: 2 | M11: =J11*K11*L11 -> 12.6 | N11: =IF(M11>=18,"КРИТИК",IF(M11>=12,"ШОШИЛИНЧ",IF(M11>=4.8,"ОДДИЙ","КЕРАКСИЗ"))) -> ШОШИЛИНЧ | O11: 12 | P11: 10 | Q11: 12000 | R11: =Q11*'3-ХИСОБ'!$B$9 -> 6000 | S11: 10 | T11: =S11*12 -> 120 | U11: =IF(T11=0,0,(R11-T11)/T11) -> 49
A12: 10 | B12: C1 | C12: ЛИД ЙИҒУВЧИ (Telegram + WhatsApp + Instagram) | D12: В. САВДО | E12: Уч канал (Telegram, WhatsApp, Instagram Direct) га келган ҳар сўровни ушлаб, мижоз номи, талаб ва телефонини ажратиб CRM'га ёзади, менежерга бириктиради ва 2 соат ичида жавоб берилмаса эслатади. | F12: Аудит: янги мижоз сўровлари менежернинг шахсий телефони ва дафтарчасида қолади — AmoCRM'га тушмайди. 12 ойда фақат 0–5 та янги B2B мижоз қўшилган. | G12: n8n + WhatsApp Business API + Instagram + AmoCRM/Bitrix24 + Claude | H12: B2B савдо бўлими | I12: ЯРАТИЛМАГАН | J12: 8 | K12: 0.8 | L12: 3 | M12: =J12*K12*L12 -> 19.2 | N12: =IF(M12>=18,"КРИТИК",IF(M12>=12,"ШОШИЛИНЧ",IF(M12>=4.8,"ОДДИЙ","КЕРАКСИЗ"))) -> КРИТИК | O12: 10 | P12: 8 | Q12: 12500 | R12: =Q12*'3-ХИСОБ'!$B$9 -> 6250 | S12: 15 | T12: =S12*12 -> 180 | U12: =IF(T12=0,0,(R12-T12)/T12) -> 33.722222
A13: 11 | B13: C2 | C13: ПРОГНОЗ ВА МАҚСАД ТАРҚАТУВЧИ | D13: В. САВДО | E13: Эски сотув маълумотини ўқийди, мавсумийликни топади, келгуси ой ва чоракка прогноз беради, компания режасини ҳар менежерга кунлик рақамгача бўлиб беради ва бажарилишини кузатади. | F13: Аудит: йиллик ҳам, чораклик ҳам сотув прогнози умуман тайёрланмайди. Ой режалари бор, лекин прогнозга эмас, ҳисга асосланган. | G13: Claude/ChatGPT + Excel + SAP B1 + n8n | H13: Муҳаммад | I13: ЯРАТИЛМАГАН | J13: 7 | K13: 0.9 | L13: 2 | M13: =J13*K13*L13 -> 12.6 | N13: =IF(M13>=18,"КРИТИК",IF(M13>=12,"ШОШИЛИНЧ",IF(M13>=4.8,"ОДДИЙ","КЕРАКСИЗ"))) -> ШОШИЛИНЧ | O13: 12 | P13: 6 | Q13: 9000 | R13: =Q13*'3-ХИСОБ'!$B$9 -> 4500 | S13: 12 | T13: =S13*12 -> 144 | U13: =IF(T13=0,0,(R13-T13)/T13) -> 30.25
A14: 12 | B14: C3 | C14: ЎЛИК ЗАХИРА СОТУВ АГЕНТИ | D14: В. САВДО | E14: 365 кундан ортиқ турган товарни рўйхатлайди, ҳар бирига чегирма нархи ва мақсадли мижоз рўйхатини тайёрлайди, ҳафтада бир марта таклиф хати юборади ва жавобларни санайди. | F14: Ўлчанган далил: 365+ кун турган ўлик захира $45,003 (127 позиция); умумий захира $486,733; захира айланиши йилига атиги 1.43 марта = 256 кунлик мол. | G14: Claude + Excel + n8n + WhatsApp/Email | H14: Ғиёсиддин + Отабек | I14: ЯРАТИЛМАГАН | J14: 9 | K14: 0.8 | L14: 3 | M14: =J14*K14*L14 -> 21.6 | N14: =IF(M14>=18,"КРИТИК",IF(M14>=12,"ШОШИЛИНЧ",IF(M14>=4.8,"ОДДИЙ","КЕРАКСИЗ"))) -> КРИТИК | O14: 10 | P14: 6 | Q14: 18000 | R14: =Q14*'3-ХИСОБ'!$B$9 -> 9000 | S14: 10 | T14: =S14*12 -> 120 | U14: =IF(T14=0,0,(R14-T14)/T14) -> 74
... A23: 21 | B23: G1 | C23: ЭГАСИНИНГ ШАХСИЙ АССИСТЕНТИ | D23: Ж. ШАХСИЙ | E23: Эгасининг почтасини сараладi, жавоб лойиҳаларини ёзади, кун тартибини тузади, келишувларни эслатади, ўқиш режасини кузатади ва ҳафтада бир марта «бу ҳафта вақтингиз қаерга кетди» ҳисоботини беради. | F23: Аудит: Эгаси ҳафтасига 70+ соат ишлайди ва бу вақт асосан «ёнғин ўчириш»га кетади — молия ва назоратга эмас. Мақсад: 2027 йилга қадар ҳафтасига 10 соатдан кам иштирок. | G23: Claude (Project) + Outlook (M365) + n8n | H23: Эгаси | I23: ЯРАТИЛМАГАН | J23: 6 | K23: 0.9 | L23: 3 | M23: =J23*K23*L23 -> 16.2 | N23: =IF(M23>=18,"КРИТИК",IF(M23>=12,"ШОШИЛИНЧ",IF(M23>=4.8,"ОДДИЙ","КЕРАКСИЗ"))) -> ШОШИЛИНЧ | O23: 8 | P23: 20 | Q23: 0 | R23: =Q23*'3-ХИСОБ'!$B$9 -> 0 | S23: 10 | T23: =S23*12 -> 120 | U23: =IF(T23=0,0,(R23-T23)/T23) -> -1
C24: ЖАМИ | O24: =SUM(O3:O23) -> 221 | P24: =SUM(P3:P23) -> 226 | Q24: =SUM(Q3:Q23) -> 148000 | R24: =SUM(R3:R23) -> 74000 | S24: =SUM(S3:S23) -> 201 | T24: =SUM(T3:T23) -> 2412 | U24: =IF(T24=0,0,(R24-T24)/T24) -> 29.679934

Sheet 3-ХИСОБ
A1: ПУЛ ВА ВАҚТ ҲИСОБИ — ФАРАЗЛАР ВА ФОРМУЛАЛАР
A2: КЎРСАТКИЧ | B2: ҚИЙМАТ | C2: БИРЛИК | D2: ИЗОҲ / МАНБА
A3: КОМПАНИЯ АСОСИ (SAP B1, янв–май 2026)
A4: Йиллик айланма (run-rate) | B4: 1190000 | C4: $ | D4: SAP B1: 5 ойда $496.7K → йилликка ўтказилган. Манба: Эгаси юклаган P&L файли
A5: Соф фойда, йиллик | B5: 107000 | C5: $ | D5: Соф маржа 9.0%. Манба: ўша P&L
A6: Ойлик доимий харажат (OpEx) | B6: 29500 | C6: $ | D6: $32,040 ойлик OpEx'дан бир марталик $12.7K чиқарилгандан кейин
A7: Ходим сони | B7: 22 | C7: киши | D7: Эгаси берган рақам
A8: Захира қиймати (таннархда) | B8: 486733 | C8: $ | D8: 22.08.2026 омбор файли, 935 позиция, 8,474 дона
A9: РЕАЛЛАШИШ КОЭФФИЦИЕНТИ | B9: 0.5 | C9: × | D9: ЭНГ МУҲИМ КАТАК. Ҳисобланган фойданинг қанча қисми ҳақиқатан келади деб ҳисоблаймиз. 0.5 = яримини оламиз (эҳтиёткор). 1.0 = ҳаммаси келади (оптимист). Ўзгартиринг — 2-варақдаги «РЕАЛ фойда» устуни қайта ҳисобланади.
A11: ВАҚТ ҲИСОБИ
A12: Барча агентлар тежайдиган вақт, ойига | B12: =SUM('2-АГЕНТЛАР'!P3:P23) -> 226 | C12: соат | D12: 2-варақдан автоматик
A13: Шундан Эгасининг вақти (тахмин 40%) | B13: =B12*0.4 -> 90.4 | C13: соат | D13: A1, A3, B1, D1, E2, G1 агентлари асосан Эгасининг вақтини бўшатади. 40% — ФАРАЗ, ўлчанмаган.
A14: Эгасининг ҳозирги ҳафталик иши | B14: 70 | C14: соат | D14: Аудит: 70+ соат/ҳафта
A15: Агентлардан кейинги ҳафталик иш | B15: =MAX(0,B14-(B13/4.33)) -> 49.122402 | C15: соат | D15: Ҳозирги минус тежалган вақт ÷ 4.33 ҳафта
A17: ПУЛ ҲИСОБИ
A18: Йиллик фойда — МАКСИМАЛ (назарий) | B18: =SUM('2-АГЕНТЛАР'!Q3:Q23) -> 148000 | C18: $ | D18: Ҳамма агент 100% ишлаган ҳолда
A19: Йиллик фойда — РЕАЛ (коэффициент билан) | B19: =B18*B9 -> 74000 | C19: $ | D19: Максимал × реаллашиш коэффициенти
A20: Йиллик харажат (агент + лицензия) | B20: ='4-БЮДЖЕТ'!D13 -> 7080 | C20: $ | D20: 4-БЮДЖЕТ варағидаги 2-ВАРИАНТ (тавсия этилган) йиллик жамиси. 2-варақдаги ойлик харажат устуни фақат агентнинг ўз API харажати — лицензия ва одам ҳақи унда йўқ, шунинг учун иккита рақам фарқ қилади.
A21: СОФ ЮТУҚ, йиллик | B21: =B19-B20 -> 66920 | C21: $ | D21: Реал фойда минус харажат
A22: ROI (ҳар 1 доллардан қайтим) | B22: =IF(B20=0,0,B21/B20) -> 9.4519774 | C22: × | D22: Соф ютуқ ÷ харажат
A23: Ўзини қоплаш муддати | B23: =IF(B19=0,0,B20/(B19/12)) -> 1.1481081 | C23: ой | D23: Йиллик харажат ÷ (реал фойда ÷ 12)
A25: ТЕКШИРУВ
A26: Реал фойда — айланманинг % и | B26: =IF(B4=0,0,B19/B4) -> 0.062184874 | C26: % | D26: Агар 10% дан ошса — фаразлар жуда оптимист, қайта кўринг
A27: Реал фойда — соф фойданинг % и | B27: =IF(B5=0,0,B19/B5) -> 0.69158879 | C27: % | D27: 100% дан ошса — рақамга ишонманг, коэффициентни туширинг

Sheet 4-БЮДЖЕТ
A1: БЮДЖЕТ — 3 ВАРИАНТ · нархлар 25.08.2026 ҳолатига, расмий саҳифалардан
A2: ВОСИТА (нима учун) | B2: НАРХ ҚОИДАСИ | C2: 1-ВАРИАНТ МИНИМАЛ, $/ой | D2: 2-ВАРИАНТ ТАВСИЯ ЭТИЛГАН, $/ой | E2: 3-ВАРИАНТ ТЎЛИҚ, $/ой | F2: ИЗОҲ
A3: Claude Team — стандарт ўрин | B3: $20/ўрин/ой (йиллик тўлов) ёки $25 (ойлик). 2–150 ўрин. | C3: 60 | D3: 100 | E3: 200 | F3: Расмий: claude.com/pricing. 1-вариант 3 ўрин, 2-вариант 5 ўрин, 3-вариант 10 ўрин.
A4: Claude API — агентларнинг «мияси» | B4: Sonnet 5: $2 / 1 млн кирувчи сўз, $10 / 1 млн чиқувчи. Haiku 4.5: $1 / $5. | C4: 30 | D4: 60 | E4: 120 | F4: Расмий: claude.com/pricing. Оддий ажратиш ишлари Haiku'га берилса нарх 2 баравар тушади.
A5: ChatGPT Business | B5: Ҳозир фойдаланилаётган. Нархни расмий саҳифадан ТАСДИҚЛАНГ. | C5: 0 | D5: 60 | E5: 90 | F5: ТЕКШИРИЛМАГАН РАҚАМ — openai.com/pricing дан ўзингиз тасдиқланг. Бу ерга тахмин ёзилмади.
A6: n8n — уловчи (ҳуб) | B6: Ўз серверда (Community) — дастур бепул, фақат сервер ҳақи. Булутда: Starter ~$20–24/ой, Pro ~$50–60/ой. | C6: 7 | D6: 10 | E6: 60 | F6: Ўз серверда сақлаш маъқул: маълумот компаниядан чиқмайди ва ишга тушириш сони чекланмаган.
A7: Сервер (VPS, Docker) | B7: Hetzner/шунга ўхшаш — ойига ~$5–10. | C7: 7 | D7: 10 | E7: 25 | F7: 3-вариантда захира сервер ва кунлик нусха олиш қўшилган.
A8: WhatsApp Business API | B8: Ҳар суҳбат учун тўлов — Meta нархи ва провайдер комиссияси. | C8: 0 | D8: 30 | E8: 60 | F8: ТЕКШИРИЛМАГАН — Wazzup ёки бошқа провайдердан аниқ нарх сўралсин.
A9: Microsoft 365 Copilot | B9: Тахминан $30/ходим/ой (Enterprise). SMB варианти ~$18–21 деб хабар қилинган. | C9: 0 | D9: 0 | E9: 90 | F9: ТЕКШИРИЛМАГАН — microsoft.com расмий саҳифасидан тасдиқланг. Тавсия: 22 ходимга ЭМАС, 3 калит одамга.
A10: Power BI Pro (дашборд учун) | B10: Тахминан $10/ходим/ой. | C10: 0 | D10: 20 | E10: 40 | F10: ТЕКШИРИЛМАГАН. Аввал Excel + Telegram билан бошланг, кейин керак бўлса қўшинг.
A11: IT/автоматлаштириш мутахассиси | B11: Ярим ставка ёки аутсорс. | C11: 0 | D11: 300 | E11: 800 | F11: Энг катта модда. Абдулбосит ўрганса — 0. Аудит: унинг заҳираси йўқ, бу ХАВФ.
A12: ЖАМИ, ойига | C12: =SUM(C3:C11) -> 104 | D12: =SUM(D3:D11) -> 590 | E12: =SUM(E3:E11) -> 1485
A13: ЖАМИ, йилига | C13: =C12*12 -> 1248 | D13: =D12*12 -> 7080 | E13: =E12*12 -> 17820
A14: Йиллик OpEx'нинг % и | C14: =C13/('3-ХИСОБ'!$B$6*12) -> 0.0035254237 | D14: =D13/('3-ХИСОБ'!$B$6*12) -> 0.02 | E14: =E13/('3-ХИСОБ'!$B$6*12) -> 0.050338983
A16: МУҲИМ: сариқ фонли барча нарх — ТЕКШИРИЛИШИ КЕРАК. Claude нархлари 25.08.2026 да claude.com/pricing расмий саҳифасидан олинди. Microsoft, OpenAI ва WhatsApp нархлари учинчи томон манбаларидан — уларни сотиб олишдан олдин расмий саҳифадан ўзингиз тасдиқланг. Бу ҳужжатда реклама йўқ: ҳар восита учун сабаб ва арзонроқ муқобил кўрсатилган.

Sheet 5-РЕЖА
A1: 90 КУНЛИК РЕЖА — бир вақтда фақат 2 та агент
A2: БОСҚИЧ | B2: КУНЛАР | C2: АГЕНТЛАР | D2: БОСҚИЧ ТУГАГАНДА НИМА БЎЛАДИ | E2: Иш ҳажми, соат | F2: ҲОЛАТ | G2: Тугаш санаси
A3: 1-БОСҚИЧ: ПОЙДЕВОР | B3: 1–14 кун | C3: H0, A1 | D3: Ҳуб ишлайди, 3 ходим кундалик ҳисоботни ботга ёзади | E3: 22 | F3: ЯРАТИЛМАГАН
A4: 2-БОСҚИЧ: НАЗОРАТ | B4: 15–30 кун | C4: A3, B1 | D4: Топшириқлар кузатилади, барча тўлов битта каналдан ўтади | E4: 18 | F4: ЯРАТИЛМАГАН
A5: 3-БОСҚИЧ: РАҚАМ | B5: 31–45 кун | C5: A2, B2 | D5: Эгаси ҳар эрталаб 5 рақамни кўради, 30 кунлик пул календари ишлайди | E5: 20 | F5: ЯРАТИЛМАГАН
A6: 4-БОСҚИЧ: ПУЛ ЧИҚАРИШ | B6: 46–60 кун | C6: C3, B4 | D6: Ўлик захира сотувга чиқди, маълумот хатолари рўйхатга олинди | E6: 22 | F6: ЯРАТИЛМАГАН
A7: 5-БОСҚИЧ: САВДО | B7: 61–75 кун | C7: C1, C4 | D7: Ҳеч бир сўров йўқолмайди, сервис шартномалари сотилмоқда | E7: 22 | F7: ЯРАТИЛМАГАН
A8: 6-БОСҚИЧ: БОШҚАРУВ | B8: 76–90 кун | C8: B3, E2 | D8: Рақамлар солиштирилади, AI операция менежери эрталабки брифни беради | E8: 34 | F8: ЯРАТИЛМАГАН
D9: ЖАМИ ИШ ҲАЖМИ | E9: =SUM(E3:E8) -> 138
A11: ТЎХТАТИШ ҚОИДАСИ: ҳар босқич охирида И = (агент тўғри бажарган иш) ÷ (жами уриниш) ҳисобланади. И < 0.50 бўлса кейинги босқич БОШЛАНМАЙДИ — олдин сабаби топилади. Бу қоида «11 та лойиҳадан 2 таси тугалланган» тарихини такрорламаслик учун.

Sheet 6-КЕРАКСИЗ
A1: КЕРАКСИЗ АГЕНТЛАР — ПУЛ САРФЛАМАНГ · бу варақ тежайдиган пул
A2: Код | B2: АГЕНТ | C2: НИМА ВАЪДА ҚИЛИНАДИ | D2: НЕГА ЭМЖИЕМ УЧУН КЕРАК ЭМАС | E2: ЎРНИГА НИМА | F2: БАЛЛ | G2: ХУЛОСА
A3: X1 | B3: AI ОВОЗЛИ ҚЎНҒИРОҚ МАРКАЗИ | C3: Мижозларга робот овоз билан қўнғироқ қилиш / жавоб бериш | D3: Фаол B2B мижоз сони 50 гача. 50 та мижозга робот гапирса — муносабат бузилади, ютуқ нолга яқин. Primus умуман тавсия ва обрў орқали сотади. Бу пул ва вақтни ейди, натижа бермайди. | E3: Ўрнига: C4 сервис агенти — ёзма эслатма, жонли қўнғироқни одам қилади | F3: 0.6 | G3: ҚУРИЛМАСИН
A4: X2 | B4: AI ВИДЕОКУЗАТУВ ТАҲЛИЛИ | C4: Камералардаги одам ва ҳаракатни AI билан таҳлил қилиш | D4: Қиммат (сервер + лицензия), ўрнатиш узоқ, ва ҳозирги асосий муаммо — ўғирлик эмас, музлаб қолган $486K захира ва назорат йўқлиги. Аудитда камерадан келган йўқотиш умуман қайд этилмаган. | E4: Ўрнига: B4 хатолик детектори — пул ҳақиқатан қаерда йўқолаётганини кўрсатади | F4: 0.6 | G4: ҚУРИЛМАСИН
A5: X3 | B5: AI РЕЗЮМЕ САРАЛАШ (HR) | C5: Номзодлар резюмесини AI билан автоматик саралаш | D5: Йилига 3–5 та одам ёлланади. 5 та резюмени саралашга агент қуриш — 12 соат иш, 0 фойда. Классик «ўйинчоқ агент». | E5: Ўрнига: A4 давомат ва E1 KPI — мавжуд одамларни ўлчаш | F5: 0.4 | G5: ҚУРИЛМАСИН
A6: X4 | B6: 22 ХОДИМГА M365 COPILOT ЛИЦЕНЗИЯСИ | C6: Барча ходимга Microsoft 365 Copilot сотиб олиш | D6: 22 × $30 = ойига $660, йилига $7,920. Ходимларнинг кўпи Word/Excel'ни кунда очмайди — 22 ходимдан фақат 3–4 таси ўзи ишлайди. Пул сарфланади, ишлатилмайди. | E6: Ўрнига: 3–5 та калит одамга лицензия, қолганига Telegram орқали агент | F6: 0.9 | G6: ҚУРИЛМАСИН
A8: Бу 4 та агент қурилмаса — йилига тахминан $9,000–12,000 ва ~60 соат иш тежалади. Умумий қоида: агент қуришдан олдин «бу ҳафтада неча марта ишлайди?» деб сўранг. Жавоб «ойда 1–2 марта» бўлса — қурманг, қўлда қилинг.

Sheet 7-ДАШБОРД
A1: ДАШБОРД — умумий манзара (автоматик)
A2: КЎРСАТКИЧ | B2: ҚИЙМАТ | D2: ИЗОҲ
A3: Жами агент | B3: =COUNTA('2-АГЕНТЛАР'!B3:B23) -> 21 | D3: Рўйхатдаги барча агент
A4: КРИТИК | B4: =COUNTIF('2-АГЕНТЛАР'!N3:N23,"КРИТИК") -> 10 | D4: Балл ≥ 18 — биринчи навбатда
A5: ШОШИЛИНЧ | B5: =COUNTIF('2-АГЕНТЛАР'!N3:N23,"ШОШИЛИНЧ") -> 6 | D5: Балл ≥ 12
A6: ОДДИЙ | B6: =COUNTIF('2-АГЕНТЛАР'!N3:N23,"ОДДИЙ") -> 5 | D6: Балл ≥ 4.8
A8: ИШЛАЯПТИ | B8: =COUNTIF('2-АГЕНТЛАР'!I3:I23,"ИШЛАЯПТИ") -> 0 | D8: Тайёр ва ҳар куни ишлаяпти
A9: ҚУРИЛМОҚДА / ТЕСТДА | B9: =COUNTIF('2-АГЕНТЛАР'!I3:I23,"ҚУРИЛМОҚДА")+COUNTIF('2-АГЕНТЛАР'!I3:I23,"ТЕСТДА") -> 0 | D9: БУ РАҚАМ 2 ДАН ОШМАСИН — олтин қоида
A10: ЯРАТИЛМАГАН | B10: =COUNTIF('2-АГЕНТЛАР'!I3:I23,"ЯРАТИЛМАГАН") -> 21 | D10: Ҳали бошланмаган
A11: Бажарилиш даражаси | B11: =IF(COUNTA('2-АГЕНТЛАР'!B3:B23)=0,0,COUNTIF('2-АГЕНТЛАР'!I3:I23,"ИШЛАЯПТИ")/COUNTA('2-АГЕНТЛАР'!B3:B23)) -> 0 | D11: Ишлаётган агент ÷ жами агент
A13: Ойлик вақт тежови | B13: ='3-ХИСОБ'!B12 -> 226 | C13: соат | D13: Барча агент ишлаган ҳолда
A14: Йиллик реал фойда | B14: ='3-ХИСОБ'!B19 -> 74000 | C14: $ | D14: Реаллашиш коэффициенти билан
A15: Йиллик харажат | B15: ='3-ХИСОБ'!B20 -> 7080 | C15: $ | D15: Лицензия + сервер + API
A16: СОФ ЮТУҚ | B16: ='3-ХИСОБ'!B21 -> 66920 | C16: $ | D16: Фойда минус харажат
A17: ROI | B17: ='3-ХИСОБ'!B22 -> 9.4519774 | C17: × | D17: Ҳар 1 доллардан қанча қайтади
A19: БУ ҲАФТАДА НИМА ҚИЛИНАДИ?
